bagitfs.py
bagitfs-0.4.0.dist-info/LICENSE.txt
bagitfs-0.4.0.dist-info/METADATA
bagitfs-0.4.0.dist-info/WHEEL
bagitfs-0.4.0.dist-info/RECORD
