Metadata-Version: 2.1
Name: bagitfs
Version: 0.4.0
Summary: Bagit package
Author: Radim Spigel
Author-email: spigel@cesnet.cz
Requires-Python: >=3.6,<4.0
Classifier: Programming Language :: Python :: 3
Classifier: Programming Language :: Python :: 3.6
Classifier: Programming Language :: Python :: 3.7
Classifier: Programming Language :: Python :: 3.8
Classifier: Programming Language :: Python :: 3.9
Classifier: Programming Language :: Python :: 3.10
Classifier: Programming Language :: Python :: 3.11
Requires-Dist: bagit (==1.8.1)
Requires-Dist: fs (>=2.2.1,<3.0.0)
